MultiCloudOCR/__init__.py
MultiCloudOCR/ocr_ali.py
MultiCloudOCR/ocr_baidu.py
MultiCloudOCR/ocr_local.py
MultiCloudOCR-1.0.dist-info/METADATA
MultiCloudOCR-1.0.dist-info/WHEEL
MultiCloudOCR-1.0.dist-info/top_level.txt
MultiCloudOCR-1.0.dist-info/RECORD
