Metadata-Version: 2.1
Name: MultiCloudOCR
Version: 1.0
Summary: This is a package to use different OCR model, including Ali, Baidu, etc.
Home-page: https://github.com/snowroll/python-sdk.git
License: UNKNOWN
Platform: UNKNOWN
